{"data": [["2019","ind","2019","indA",0,"Health status","Demographic Characteristics","","","37.9","36.0, 39.7","41.8","39.9, 43.7",""],["2020","ind","2020","indA",0,"Health status","Demographic Characteristics","","","42.6","39.9, 45.3","43.9","41.3, 46.6",""],["2021","ind","2021","indA",0,"Health status","Demographic Characteristics","","","42.9","41.0, 44.9","45.1","43.2, 47.0",""],["2022","ind","2022","indA",0,"Health status","Demographic Characteristics","","","49.1","47., 51.1","48.8","46., 50.8",""],["2023","ind","2023","indA",0,"Health status","Demographic Characteristics","","","44.0","42.1,45.9","47.8","45.9,49.7",""],["2024","ind","2024","indA",0,"Health status","Demographic Characteristics","","","46.1","44.2, 48.1","48.4","46.5, 50.3",""]], "classes": ["Year","row_var","rowLevels","rowLevNum","selected","stat_group","col_group","new_caption","new_caption2","Female__sexA__ANYDIFF__coef","Female__sexA__ANYDIFF__se","Male__sexB__ANYDIFF__coef","Male__sexB__ANYDIFF__se","subLevels"], "names": ["Year","row_var","rowLevels","rowLevNum","selected","stat_group","col_group","new_caption","new_caption2","Female","Female","Male","Male","subLevels"], "caption": ["Percentage with functional difficulty for children under age 18 years (95% confidence intervals), United States"], "caption2": [""], "caption3": [""]}
